AUTHORS.rst
CONTRIBUTING.rst
LICENSE
MANIFEST.in
README.md
setup.cfg
setup.py
docs/Makefile
docs/authors.rst
docs/conf.py
docs/contributing.rst
docs/make.bat
lark_sdk/__init__.py
lark_sdk/lark.py
lark_sdk/lark_docs.py
lark_sdk/lark_send.py
lark_sdk/lib.py
lark_sdk.egg-info/PKG-INFO
lark_sdk.egg-info/SOURCES.txt
lark_sdk.egg-info/dependency_links.txt
lark_sdk.egg-info/not-zip-safe
lark_sdk.egg-info/top_level.txt
tests/__init__.py
tests/config.json
tests/lark_docs.json
tests/test_lark.py
tests/test_lark_docs.py
tests/test_lark_send.py
tests/utils.py