Metadata-Version: 2.1
Name: lark-sdk
Version: 0.4.1
Summary: A python sdk that implements all the features of the official documentation (not implemented).
Home-page: https://github.com/fuergaosi233/lark_sdk
Author: holegots
Author-email: gaopengyang@bytedance.com
License: MIT license
Keywords: lark_sdk
Platform: UNKNOWN
Classifier: Development Status :: 2 - Pre-Alpha
Classifier: Intended Audience :: Developers
Classifier: License :: OSI Approved :: MIT License
Classifier: Natural Language :: English
Classifier: Programming Language :: Python :: 2.7
Classifier: Programming Language :: Python :: 3
Classifier: Programming Language :: Python :: 3.5
Classifier: Programming Language :: Python :: 3.6
Classifier: Programming Language :: Python :: 3.7
Classifier: Programming Language :: Python :: 3.8
Requires-Python: >=2.7,!=3.0.*,!=3.1.*
